RyzenUtil/__init__.py
RyzenUtil/util.py
code/__init__.py
code/util.py
RyzenUtil-0.1.0.dist-info/LICENSE
RyzenUtil-0.1.0.dist-info/METADATA
RyzenUtil-0.1.0.dist-info/WHEEL
RyzenUtil-0.1.0.dist-info/top_level.txt
RyzenUtil-0.1.0.dist-info/RECORD
